ddrift/__init__.py
ddrift/_utils.py
ddrift/base.py
ddrift/results.py
ddrift/sql.py
ddrift-0.1.0.dist-info/METADATA
ddrift-0.1.0.dist-info/WHEEL
ddrift-0.1.0.dist-info/entry_points.txt
ddrift-0.1.0.dist-info/RECORD
