Metadata-Version: 2.4
Name: ddrift
Version: 0.1.0
Summary: Add your description here
Author-email: Tyler Riccio <tylerriccio8@gmail.com>
Requires-Python: >=3.11
Requires-Dist: narwhals>=1.27.1
